features_factory/.DS_Store
features_factory/__init__.py
features_factory/composed_features.py
features_factory/dependencies_error.py
features_factory/external_data_source_features.py
features_factory/feature_archetype.py
features_factory/generated_features.py
features_factory/input_data_error.py
features_factory/input_features.py
features_factory/multicomponent_features.py
features_factory/one_component_features.py
features_factory/stack.py
features_factory/stack_error.py
features_factory/stack_factory.py
features_factory/two_component_features.py
features_factory/embedded_data/__init__.py
features_factory/embedded_data/country_code_iso_alpha2.json
features_factory-2.0.1.dist-info/AUTHORS.md
features_factory-2.0.1.dist-info/LICENSE.txt
features_factory-2.0.1.dist-info/METADATA
features_factory-2.0.1.dist-info/WHEEL
features_factory-2.0.1.dist-info/top_level.txt
features_factory-2.0.1.dist-info/RECORD
