Metadata-Version: 2.1
Name: features-factory
Version: 2.0.1
Summary: A small python package that helps dealing with Machine Learning features
Home-page: https://gitlab.com/francesco-calcavecchia/features_factory
Author: Francesco Calcavecchia
Author-email: francesco086@gmail.com
License: mit
Platform: any
Classifier: Development Status :: 5 - Production/Stable
Classifier: License :: OSI Approved :: MIT License
Classifier: Programming Language :: Python :: 3.7
Classifier: Natural Language :: English
Requires-Python: >=3.5
License-File: LICENSE.txt
License-File: AUTHORS.md
Requires-Dist: numpy
Requires-Dist: pandas
Provides-Extra: deploy
Requires-Dist: wheel ; extra == 'deploy'
Requires-Dist: build ; extra == 'deploy'
Requires-Dist: twine ; extra == 'deploy'
Provides-Extra: dev
Requires-Dist: black ; extra == 'dev'
Provides-Extra: doc
Requires-Dist: mkdocs ; extra == 'doc'
Provides-Extra: test
Requires-Dist: coverage ; extra == 'test'
